ChompAI/__init__.py
ChompAI/game.py
ChompAI/p_positions_12x12.txt
ChompAI-0.0.2.dist-info/LICENSE.md
ChompAI-0.0.2.dist-info/METADATA
ChompAI-0.0.2.dist-info/WHEEL
ChompAI-0.0.2.dist-info/top_level.txt
ChompAI-0.0.2.dist-info/RECORD
