Metadata-Version: 2.1
Name: ChompAI
Version: 0.0.2
Summary: Chomp computer
Home-page: UNKNOWN
Author: purple-ish
Author-email: UNKNOWN
License: UNKNOWN
Keywords: chomp
Platform: UNKNOWN
Requires-Dist: numpy
